basicpid/__init__.py
basicpid/pid.py
basic_pid-0.2.7.dist-info/LICENSE
basic_pid-0.2.7.dist-info/METADATA
basic_pid-0.2.7.dist-info/WHEEL
basic_pid-0.2.7.dist-info/top_level.txt
basic_pid-0.2.7.dist-info/RECORD
