Metadata-Version: 2.1
Name: basic-pid
Version: 0.2.7
Summary: Standard PID Controller For Discrete Time Regulators
Home-page: https://github.com/mkner/basic-pid
Author: Mike Knerr
License: BSD
Keywords: PID,controllers,regulators,discrete time systems,mobile robotics,robotics
Platform: UNKNOWN
Classifier: Programming Language :: Python :: 3
Classifier: License :: OSI Approved :: BSD License
Classifier: Operating System :: OS Independent
License-File: LICENSE
